outliers/Outliers.py
outliers/__init__.py
outlier_101703291_thapar-1.0.1.dist-info/LICENSE.txt
outlier_101703291_thapar-1.0.1.dist-info/METADATA
outlier_101703291_thapar-1.0.1.dist-info/WHEEL
outlier_101703291_thapar-1.0.1.dist-info/entry_points.txt
outlier_101703291_thapar-1.0.1.dist-info/top_level.txt
outlier_101703291_thapar-1.0.1.dist-info/RECORD
