Metadata-Version: 2.1
Name: outlier-101703291-thapar
Version: 1.0.1
Summary: A outlier Package Project of UCS633
Home-page: UNKNOWN
Author: Krishang Dubey
Author-email: kdubey1999@gmail.com
License: MIT
Platform: UNKNOWN
Classifier: Programming Language :: Python
Classifier: Operating System :: OS Independent
Classifier: License :: OSI Approved :: Python Software Foundation License
